setup.py
dh_pipenv/__init__.py
dh_pipenv/command_line.py
dh_pipenv.egg-info/PKG-INFO
dh_pipenv.egg-info/SOURCES.txt
dh_pipenv.egg-info/dependency_links.txt
dh_pipenv.egg-info/entry_points.txt
dh_pipenv.egg-info/not-zip-safe
dh_pipenv.egg-info/top_level.txt