Metadata-Version: 1.0
Name: dh-pipenv
Version: 0.1.1
Summary: Shim between dh-virtualenv and pipenv
Home-page: http://github.com/michael-christen/dh-pipenv
Author: Michael Christen
Author-email: mchristen96@gmail.com
License: MIT
Platform: UNKNOWN
